cellmap_data/__init__.py
cellmap_data/base_dataset.py
cellmap_data/base_image.py
cellmap_data/dataloader.py
cellmap_data/dataset.py
cellmap_data/dataset_writer.py
cellmap_data/datasplit.py
cellmap_data/empty_image.py
cellmap_data/image.py
cellmap_data/image_writer.py
cellmap_data/multidataset.py
cellmap_data/mutable_sampler.py
cellmap_data/subdataset.py
cellmap_data/transforms/__init__.py
cellmap_data/transforms/augment/__init__.py
cellmap_data/transforms/augment/binarize.py
cellmap_data/transforms/augment/gaussian_blur.py
cellmap_data/transforms/augment/gaussian_noise.py
cellmap_data/transforms/augment/nan_to_num.py
cellmap_data/transforms/augment/normalize.py
cellmap_data/transforms/augment/random_contrast.py
cellmap_data/transforms/augment/random_gamma.py
cellmap_data/utils/__init__.py
cellmap_data/utils/figs.py
cellmap_data/utils/metadata.py
cellmap_data/utils/misc.py
cellmap_data/utils/sampling.py
cellmap_data/utils/view.py
cellmap_data-2025.12.12.1737.dist-info/METADATA
cellmap_data-2025.12.12.1737.dist-info/WHEEL
cellmap_data-2025.12.12.1737.dist-info/licenses/LICENSE
cellmap_data-2025.12.12.1737.dist-info/RECORD
